{
  "displayName": "Buddy Barrier",
  "description": "Grants a shield to the Pokémon and to the nearby ally Pokémon with the lowest HP when the Pokémon uses its Unite Move.",
  "tags": [],
  "special": {
    "description": "When the Pokémon uses its Unite Move, that Pokémon and the nearby ally Pokémon with the lowest HP are each granted a shidle equal to {shld} of their max HP.",
    "boons": {
      "1": {
        "shld": "20%"
      },
      "10": {
        "shld": "30%"
      },
      "20": {
        "shld": "40%"
      }
    }
  },
  "stats": {
    "hp": {
      "formula": "{lvl} * 20",
      "type": "flat"
    }
  }
}
